quickMTF/LineP_MTF.py
quickMTF/SFR_MTF.py
quickMTF/__init__.py
quickMTF/quickMTF.py
quickMTF-2023.3.3.dist-info/METADATA
quickMTF-2023.3.3.dist-info/WHEEL
quickMTF-2023.3.3.dist-info/top_level.txt
quickMTF-2023.3.3.dist-info/RECORD
