Metadata-Version: 2.1
Name: quickMTF
Version: 2023.3.3
Summary: quick MTF for Line_pair and SFR
Home-page: https://github.com/Lorrytoolcenter/quickMTF
Author: lorry_rui
Author-email: lorryruizhihua@gmail.com
License: UNKNOWN
Platform: UNKNOWN
Classifier: Programming Language :: Python :: 3
Classifier: License :: OSI Approved :: MIT License
Classifier: Operating System :: OS Independent
Requires-Python: >=3.6
